MANIFEST.in
README.txt
setup.py
docs/HISTORY.txt
docs/INSTALL.txt
docs/LICENSE.GPL
docs/LICENSE.txt
src/collective/__init__.py
src/collective.onlogin.egg-info/PKG-INFO
src/collective.onlogin.egg-info/SOURCES.txt
src/collective.onlogin.egg-info/dependency_links.txt
src/collective.onlogin.egg-info/entry_points.txt
src/collective.onlogin.egg-info/namespace_packages.txt
src/collective.onlogin.egg-info/not-zip-safe
src/collective.onlogin.egg-info/requires.txt
src/collective.onlogin.egg-info/top_level.txt
src/collective/onlogin/__init__.py
src/collective/onlogin/configure.zcml
src/collective/onlogin/controlpanel.py
src/collective/onlogin/events.py
src/collective/onlogin/interfaces.py
src/collective/onlogin/testing.py
src/collective/onlogin/Extensions/Install.py
src/collective/onlogin/profiles/default/browserlayer.xml
src/collective/onlogin/profiles/default/controlpanel.xml
src/collective/onlogin/profiles/default/metadata.xml
src/collective/onlogin/profiles/default/registry.xml
src/collective/onlogin/profiles/default/skins.xml
src/collective/onlogin/profiles/uninstall/registry.xml
src/collective/onlogin/profiles/uninstall/skins.xml
src/collective/onlogin/skins/collective_onlogin/popupforms.js
src/collective/onlogin/tests/__init__.py
src/collective/onlogin/tests/test_events.py
src/collective/onlogin/tests/test_install.py