Metadata-Version: 1.0
Name: collective.onlogin
Version: 1.0
Summary: This package allows the configuration of HTTP redirects after user logged in into Plone site.
Home-page: https://github.com/martinschoel/collective.onlogin
Author: Vitaliy Podoba
Author-email: vitaliy@martinschoel.com
License: GPL
Keywords: redirect login
Platform: UNKNOWN
Classifier: Framework :: Plone
Classifier: Programming Language :: Python
